squarequant/__init__.py
squarequant/api.py
squarequant/constants.py
squarequant/core/__init__.py
squarequant/core/base.py
squarequant/core/metrics.py
squarequant/data/__init__.py
squarequant/data/data.py
squarequant/monte_carlo/__init__.py
squarequant/monte_carlo/montecarlo.py
squarequant/utils/__init__.py
squarequant/utils/helpers.py
squarequant/var/__init__.py
squarequant/var/valueatrisk.py
squarequant-0.2.3.dist-info/licenses/LICENSE
squarequant-0.2.3.dist-info/METADATA
squarequant-0.2.3.dist-info/WHEEL
squarequant-0.2.3.dist-info/top_level.txt
squarequant-0.2.3.dist-info/RECORD
