Metadata-Version: 2.4
Name: squarequant
Version: 0.2.3
Summary: A Python package for financial risk metrics and stock data analysis
Home-page: https://github.com/SquareQuant/squarequant-package
Author: Gabriel Bosch
Author-email: Gabriel Bosch <contact@squarequant.org>
Project-URL: Documentation, https://www.squarequant.org
Project-URL: Bug Tracker, https://github.com/SquareQuant/squarequant-package/issues
Project-URL: Homepage, https://github.com/SquareQuant/squarequant-package
Classifier: Programming Language :: Python :: 3
Classifier: Programming Language :: Python :: 3.7
Classifier: Programming Language :: Python :: 3.8
Classifier: Programming Language :: Python :: 3.9
Classifier: Programming Language :: Python :: 3.10
Classifier: Programming Language :: Python :: 3.11
Classifier: Programming Language :: Python :: 3.12
Classifier: Programming Language :: Python :: 3.13
Classifier: License :: OSI Approved :: MIT License
Classifier: Operating System :: OS Independent
Classifier: Topic :: Office/Business :: Financial :: Investment
Classifier: Topic :: Scientific/Engineering :: Information Analysis
Classifier: Intended Audience :: Financial and Insurance Industry
Classifier: Intended Audience :: Science/Research
Classifier: Development Status :: 4 - Beta
Requires-Python: >=3.7
License-File: LICENSE
Requires-Dist: pandas>=1.0.0
Requires-Dist: numpy>=1.18.0
Requires-Dist: yfinance>=0.1.63
Requires-Dist: scipy>=1.5.0
Requires-Dist: scikit-learn>=1.5.0
Requires-Dist: matplotlib>=3.3.0
Requires-Dist: statsmodels>=0.12.0
Requires-Dist: requests>=2.25.0
Provides-Extra: optimization
Requires-Dist: cvxpy>=1.0.0; extra == "optimization"
Provides-Extra: dev
Requires-Dist: pytest>=6.0.0; extra == "dev"
Requires-Dist: black>=21.5b2; extra == "dev"
Requires-Dist: flake8>=3.9.0; extra == "dev"
Requires-Dist: sphinx>=4.0.0; extra == "dev"
Requires-Dist: sphinx-rtd-theme>=0.5.0; extra == "dev"
Requires-Dist: sphinx-autodoc-typehints>=1.22.0; extra == "dev"
Requires-Dist: myst-parser>=1.0.0; extra == "dev"
Requires-Dist: pytest-cov>=2.12.0; extra == "dev"
Dynamic: author
Dynamic: home-page
Dynamic: license-file
Dynamic: requires-python
